setup.py
dcg_probability/Binomialdistribution.py
dcg_probability/Gaussiandistribution.py
dcg_probability/Generaldistribution.py
dcg_probability/__init__.py
dcg_probability.egg-info/PKG-INFO
dcg_probability.egg-info/SOURCES.txt
dcg_probability.egg-info/dependency_links.txt
dcg_probability.egg-info/not-zip-safe
dcg_probability.egg-info/top_level.txt