Metadata-Version: 1.0
Name: dcg-probability
Version: 1.0
Summary: Gaussian and Binomial distributions
Home-page: UNKNOWN
Author: Dane Gunther
Author-email: danecgunther@gmail.com
License: UNKNOWN
Platform: UNKNOWN
